requirements.txt
names_matcher/__init__.py
names_matcher/__main__.py
names_matcher/algorithm.py
names_matcher/metadata.py
names_matcher/tests/__init__.py
names_matcher/tests/test_algorithm.py
names_matcher/tests/test_main.py
names_matcher-2.0.13.dist-info/LICENSE
names_matcher-2.0.13.dist-info/METADATA
names_matcher-2.0.13.dist-info/WHEEL
names_matcher-2.0.13.dist-info/top_level.txt
names_matcher-2.0.13.dist-info/RECORD
