Metadata-Version: 2.1
Name: names-matcher
Version: 2.0.13
Summary: Fuzzily biject people's names between two lists.
Home-page: https://github.com/athenianco/names-matcher
Author: Athenian
Author-email: vadim@athenian.co
License: Apache-2.0
Keywords: fuzzy matching
Classifier: Development Status :: 4 - Beta
Classifier: Programming Language :: Python :: 3.8
Classifier: Programming Language :: Python :: 3.9
Classifier: Programming Language :: Python :: 3.10
Classifier: Programming Language :: Python :: 3.11
Classifier: License :: OSI Approved :: Apache Software License
License-File: LICENSE
Requires-Dist: numpy (>=1.20.0)
Requires-Dist: lapjv (<2.0,>=1.3.14)
Requires-Dist: rapidfuzz (<3.0,>=2.0.0)
Requires-Dist: unidecode (<2.0,>=1.0.0)
